muttr/__init__.py
muttr/__main__.py
muttr/args.py
muttr/changer.py
muttr/client.py
muttr/config.py
muttr/daemon.py
muttr/muter.py
muttr/sound.py
muttr/data/config.toml
muttr/data/sounds/changed.wav
muttr/data/sounds/muted.wav
muttr/data/sounds/unmuted.wav
muttr-1.0.0.dist-info/LICENSE
muttr-1.0.0.dist-info/METADATA
muttr-1.0.0.dist-info/WHEEL
muttr-1.0.0.dist-info/entry_points.txt
muttr-1.0.0.dist-info/top_level.txt
muttr-1.0.0.dist-info/RECORD
