Metadata-Version: 2.1
Name: muttr
Version: 1.0.0
Summary: Muttr. Mute all inputs, or change audio outputs and inputs easily.
Home-page: https://github.com/kuralabs/muttr
Author: KuraLabs S.R.L
Author-email: info@kuralabs.io
Keywords: muttr
Classifier: Development Status :: 4 - Beta
Classifier: Intended Audience :: Developers
Classifier: License :: OSI Approved :: Apache Software License
Classifier: Natural Language :: English
Classifier: Operating System :: POSIX :: Linux
Classifier: Programming Language :: Python :: 3
License-File: LICENSE
Requires-Dist: pulsectl
Requires-Dist: pynput
Requires-Dist: setuptools
Requires-Dist: tomli
Requires-Dist: objns
Requires-Dist: colorlog
